[
    {  
    "name": "Pizza",
    "url": "https://firebasestorage.googleapis.com/v0/b/food-first-b91f2.appspot.com/o/img%2Fcategory%2Fpizza.png?alt=media&token=ff526265-79e3-4519-910d-c0b7cf07d2e0"
},
{ 
    "name": "Steak",
    "url": "https://firebasestorage.googleapis.com/v0/b/food-first-b91f2.appspot.com/o/img%2Fcategory%2Fsteak.png?alt=media&token=95992ea7-452c-4f5b-9381-c95ad299a4d6"
},
{
    "name": "Dessert",
    "url": "https://firebasestorage.googleapis.com/v0/b/food-first-b91f2.appspot.com/o/img%2Fcategory%2Fdonut.png?alt=media&token=06f8399b-0921-4f90-9303-f5c98d78e13c"
},
{ 
    "name": "A La Carte",
    "url": "https://firebasestorage.googleapis.com/v0/b/food-first-b91f2.appspot.com/o/img%2Fcategory%2Ffood.png?alt=media&token=dd10830d-7f4f-4e28-a373-ad8f23ca433a"
},
{ 
    "name": "Drinks",
    "url": "https://firebasestorage.googleapis.com/v0/b/food-first-b91f2.appspot.com/o/img%2Fcategory%2Fchocolate.png?alt=media&token=c64dbf38-954a-474e-a16d-3a42bdce1256"
}
]